aisle/__init__.py
aisle/analyser/__init__.py
aisle/analyser/__pycache__/__init__.cpython-312.pyc
aisle/analyser/__pycache__/exceptions.cpython-312.pyc
aisle/analyser/__pycache__/interfaces.cpython-312.pyc
aisle/analyser/entities/__init__.py
aisle/analyser/entities/__pycache__/__init__.cpython-312.pyc
aisle/analyser/entities/__pycache__/containers.cpython-312.pyc
aisle/analyser/entities/__pycache__/context.cpython-312.pyc
aisle/analyser/entities/__pycache__/deployment.cpython-312.pyc
aisle/analyser/entities/__pycache__/links.cpython-312.pyc
aisle/analyser/entities/__pycache__/project.cpython-312.pyc
aisle/analyser/entities/__pycache__/styling.cpython-312.pyc
aisle/analyser/entities/containers.py
aisle/analyser/entities/context.py
aisle/analyser/entities/deployment.py
aisle/analyser/entities/links.py
aisle/analyser/entities/project.py
aisle/analyser/entities/styling.py
aisle/analyser/exceptions.py
aisle/analyser/impl/__init__.py
aisle/analyser/impl/__pycache__/__init__.cpython-312.pyc
aisle/analyser/impl/__pycache__/analyser.cpython-312.pyc
aisle/analyser/impl/analyser.py
aisle/analyser/interfaces.py
aisle/codegen/__init__.py
aisle/codegen/__pycache__/__init__.cpython-312.pyc
aisle/codegen/__pycache__/interfaces.cpython-312.pyc
aisle/codegen/__pycache__/utils.cpython-312.pyc
aisle/codegen/impl/__init__.py
aisle/codegen/impl/__pycache__/__init__.cpython-312.pyc
aisle/codegen/impl/__pycache__/mermaid.cpython-312.pyc
aisle/codegen/impl/__pycache__/plantuml.cpython-312.pyc
aisle/codegen/impl/mermaid.py
aisle/codegen/impl/plantuml.py
aisle/codegen/interfaces.py
aisle/codegen/utils.py
aisle/lexer/__init__.py
aisle/lexer/__pycache__/__init__.cpython-312.pyc
aisle/lexer/__pycache__/exceptions.cpython-312.pyc
aisle/lexer/__pycache__/interfaces.cpython-312.pyc
aisle/lexer/__pycache__/tokens.cpython-312.pyc
aisle/lexer/exceptions.py
aisle/lexer/impl/__init__.py
aisle/lexer/impl/__pycache__/__init__.cpython-312.pyc
aisle/lexer/impl/__pycache__/lexer.cpython-312.pyc
aisle-0.1.1.dist-info/entry_points.txt
aisle-0.1.1.dist-info/LICENSE
aisle-0.1.1.dist-info/METADATA
aisle-0.1.1.dist-info/WHEEL
aisle-0.1.1.dist-info/RECORD
