Metadata-Version: 2.3
Name: aisle
Version: 0.1.1
Summary: Easy AaC tool for creating architecture diagrams
License: GNU GPL v3.0
Author: Tapeline
Author-email: yt.redstone.mail@gmail.com
Requires-Python: >=3.12,<4.0
Classifier: Programming Language :: Python :: 3.12
Classifier: Operating System :: OS Independent
Classifier: Development Status :: 3 - Alpha
Classifier: Environment :: Console
Classifier: Intended Audience :: Developers
Classifier: License :: OSI Approved :: GNU General Public License v3 (GPLv3)
Classifier: Topic :: Documentation
Classifier: Topic :: Software Development :: Code Generators
Classifier: Topic :: Software Development :: Documentation
Requires-Dist: click (>=8.1.8,<9.0.0)
Project-URL: Homepage, https://tapeline.github.io/Aisle
Project-URL: Issues, https://github.com/Tapeline/Aisle/issues
